mockfirestore/__init__.py
mockfirestore/_helpers.py
mockfirestore/_transformations.py
mockfirestore/async_client.py
mockfirestore/async_collection.py
mockfirestore/async_document.py
mockfirestore/async_query.py
mockfirestore/async_transaction.py
mockfirestore/client.py
mockfirestore/collection.py
mockfirestore/document.py
mockfirestore/exceptions.py
mockfirestore/query.py
mockfirestore/transaction.py
tests/__init__.py
tests/test_async_collection_reference.py
tests/test_async_document_reference.py
tests/test_async_mock_client.py
tests/test_async_query.py
tests/test_async_transaction.py
tests/test_collection_reference.py
tests/test_document_reference.py
tests/test_document_snapshot.py
tests/test_mock_client.py
tests/test_timestamp.py
tests/test_transaction.py
mock_firestore_async-0.11.3.dist-info/LICENSE
mock_firestore_async-0.11.3.dist-info/METADATA
mock_firestore_async-0.11.3.dist-info/WHEEL
mock_firestore_async-0.11.3.dist-info/top_level.txt
mock_firestore_async-0.11.3.dist-info/RECORD
